{"cameraMode":{"drawMode":0,"name":"Shaded","section":"Shading Mode"},"sceneLighting":true,"audioPlay":false,"sceneViewState":{"m_AlwaysRefresh":false,"showFog":true,"showSkybox":true,"showFlares":true,"showImageEffects":true,"showParticleSystems":true,"showVisualEffectGraphs":true,"m_FxEnabled":true},"in2DMode":false,"pivot":{"x":4.489999771118164,"y":0.5000004768371582,"z":0.5099999904632568},"rotation":{"x":-0.019720574840903283,"y":-0.797228991985321,"z":0.602790117263794,"w":-0.026081612333655359},"size":9.006611824035645,"orthographic":false}