{"cameraMode":{"drawMode":0,"name":"Shaded","section":"Shading Mode"},"sceneLighting":true,"audioPlay":false,"sceneViewState":{"m_AlwaysRefresh":false,"showFog":true,"showSkybox":true,"showFlares":true,"showImageEffects":true,"showParticleSystems":true,"showVisualEffectGraphs":true,"m_FxEnabled":true},"in2DMode":false,"pivot":{"x":1.2670804262161255,"y":0.6092759370803833,"z":-0.42716360092163088},"rotation":{"x":0.19561266899108888,"y":-0.1518269181251526,"z":0.03020467422902584,"w":0.9686150550842285},"size":2.4380955696105959,"orthographic":false}